exceptions.py
algorithms.py
__init__.py
graph_helpers.py
absorbing_centrality/exceptions.py
absorbing_centrality/algorithms.py
absorbing_centrality/__init__.py
absorbing_centrality/graph_helpers.py
absorbing_centrality/.ropeproject/globalnames
absorbing_centrality/.ropeproject/objectdb
absorbing_centrality/.ropeproject/history
absorbing_centrality/.ropeproject/config.py
absorbing_centrality-0.1.0.dist-info/WHEEL
absorbing_centrality-0.1.0.dist-info/RECORD
absorbing_centrality-0.1.0.dist-info/METADATA
absorbing_centrality-0.1.0.dist-info/DESCRIPTION.rst
absorbing_centrality-0.1.0.dist-info/metadata.json
absorbing_centrality-0.1.0.dist-info/pbr.json
absorbing_centrality-0.1.0.dist-info/top_level.txt
