Metadata-Version: 2.0
Name: absorbing-centrality
Version: 0.1.0
Summary: An implementation of the absorbing random-walk centrality measure for graphs.
Home-page: https://github.com/harrymvr/absorbing-centrality
Author: Charalampos Mavroforakis
Author-email: cmav@bu.edu
License: ISC
Keywords: graph mining,node centrality,random walks,algorithms,data mining
Platform: UNKNOWN
Classifier: Intended Audience :: Developers
Classifier: Intended Audience :: Science/Research
Classifier: Operating System :: Unix
Classifier: Operating System :: POSIX
Classifier: Programming Language :: Python :: 2
Classifier: Programming Language :: Python :: 2.7
Classifier: Programming Language :: Python :: 3
Classifier: Programming Language :: Python :: 3.4
Classifier: License :: OSI Approved :: ISC License (ISCL)
Classifier: Topic :: Scientific/Engineering :: Information Analysis
Classifier: Natural Language :: English
Requires-Dist: networkx (>=1.9.1)
Requires-Dist: numpy (==1.9.2)
Requires-Dist: scipy (==0.16)
Provides-Extra: tests
Requires-Dist: nose; extra == 'tests'
